LICENSE
MANIFEST.in
README.md
pyproject.toml
requirements.json
setup.py
mbapy/__init__.py
mbapy/__version__.py
mbapy/base.py
mbapy/file.py
mbapy/game.py
mbapy/paper.py
mbapy/plot.py
mbapy/web.py
mbapy.egg-info/PKG-INFO
mbapy.egg-info/SOURCES.txt
mbapy.egg-info/dependency_links.txt
mbapy.egg-info/entry_points.txt
mbapy.egg-info/requires.txt
mbapy.egg-info/top_level.txt
mbapy/bio/__init__.py
mbapy/bio/high_level.py
mbapy/bio/peptide.py
mbapy/chem/__init__.py
mbapy/chem/formula.py
mbapy/dl_torch/__init__.py
mbapy/dl_torch/bb.py
mbapy/dl_torch/data.py
mbapy/dl_torch/hyper_search.py
mbapy/dl_torch/loss.py
mbapy/dl_torch/m.py
mbapy/dl_torch/optim.py
mbapy/dl_torch/utils.py
mbapy/dl_torch/arch/__init__.py
mbapy/dl_torch/arch/CL/__init__.py
mbapy/dl_torch/arch/CL/builder.py
mbapy/dl_torch/arch/CL/trainer.py
mbapy/dl_torch/arch/CLIP/__init__.py
mbapy/dl_torch/arch/CLIP/builder.py
mbapy/dl_torch/arch/CLIP/trainer.py
mbapy/dl_torch/paper/__init__.py
mbapy/dl_torch/paper/bb.py
mbapy/file_utils/__init__.py
mbapy/file_utils/image.py
mbapy/file_utils/video.py
mbapy/plot_utils/__init__.py
mbapy/plot_utils/bar_utils.py
mbapy/plot_utils/line_utils.py
mbapy/plot_utils/scatter_utils.py
mbapy/sci_instrument/__init__.py
mbapy/sci_instrument/_base.py
mbapy/sci_instrument/_utils.py
mbapy/sci_instrument/hplc/Easychrom.py
mbapy/sci_instrument/hplc/SCIEX.py
mbapy/sci_instrument/hplc/__init__.py
mbapy/sci_instrument/hplc/_base.py
mbapy/sci_instrument/hplc/_utils.py
mbapy/sci_instrument/hplc/waters.py
mbapy/sci_instrument/mass/Agilent.py
mbapy/sci_instrument/mass/SCIEX.py
mbapy/sci_instrument/mass/__init__.py
mbapy/sci_instrument/mass/_base.py
mbapy/sci_instrument/mass/_utils.py
mbapy/sci_utils/__init__.py
mbapy/sci_utils/paper_download.py
mbapy/sci_utils/paper_parse.py
mbapy/sci_utils/paper_search.py
mbapy/scripts/__init__.py
mbapy/scripts/__main__.py
mbapy/scripts/_main_.py
mbapy/scripts/_script_utils_.py
mbapy/scripts/auto_cpp.py
mbapy/scripts/avif.py
mbapy/scripts/batch_cmd.py
mbapy/scripts/cluster.py
mbapy/scripts/cmd_runner.py
mbapy/scripts/cnipa.py
mbapy/scripts/copy_file.py
mbapy/scripts/duitang.py
mbapy/scripts/extract_dir.py
mbapy/scripts/extract_paper.py
