Metadata-Version: 2.1
Name: mbapy
Version: 0.11.5
Summary: MyBA in Python - A comprehensive utility library
Home-page: https://github.com/BHM-Bob/BA_PY
Author: BHM-Bob G
Author-email: BHM-Bob G <bhmfly@foxmail.com>
Maintainer-email: BHM-Bob G <bhmfly@foxmail.com>
License: MIT
Project-URL: Homepage, https://github.com/BHM-Bob/BA_PY
Project-URL: Repository, https://github.com/BHM-Bob/BA_PY
Project-URL: Documentation, https://mbapy.readthedocs.io
Project-URL: Bug Tracker, https://github.com/BHM-Bob/BA_PY/issues
Project-URL: Changelog, https://github.com/BHM-Bob/BA_PY/blob/main/docs/release_notes
Keywords: mbapy,Utilities,plot,stats,pdf,paper,crawler,biology,game
Platform: any
Classifier: Development Status :: 4 - Beta
Classifier: Intended Audience :: Science/Research
Classifier: Topic :: Utilities
Classifier: License :: OSI Approved :: MIT License
Classifier: Programming Language :: Python :: 3
Classifier: Programming Language :: Python :: 3.8
Classifier: Programming Language :: Python :: 3.9
Classifier: Programming Language :: Python :: 3.10
Classifier: Programming Language :: Python :: 3.11
Classifier: Programming Language :: Python :: 3.12
Classifier: Operating System :: OS Independent
Requires-Python: >=3.8, <3.14
Provides-Extra: none
Provides-Extra: bio
Provides-Extra: game
Provides-Extra: full
Provides-Extra: dev
License-File: LICENSE
